aind_hierarchical_bootstrap/__init__.py
aind_hierarchical_bootstrap/bootstrap.py
aind_hierarchical_bootstrap/make_dataset.py
aind_hierarchical_bootstrap/speed_test.py
aind_hierarchical_bootstrap/stats.py
aind_hierarchical_bootstrap-0.0.7.dist-info/licenses/LICENSE
aind_hierarchical_bootstrap-0.0.7.dist-info/METADATA
aind_hierarchical_bootstrap-0.0.7.dist-info/WHEEL
aind_hierarchical_bootstrap-0.0.7.dist-info/top_level.txt
aind_hierarchical_bootstrap-0.0.7.dist-info/RECORD
